setup.py
module_auth/DBConnections.py
module_auth/Encryption.py
module_auth/Response.py
module_auth/__init__.py
module_auth/app.py
module_auth/auth_model.py
module_auth.egg-info/PKG-INFO
module_auth.egg-info/SOURCES.txt
module_auth.egg-info/dependency_links.txt
module_auth.egg-info/not-zip-safe
module_auth.egg-info/requires.txt
module_auth.egg-info/top_level.txt