Metadata-Version: 2.1
Name: module-auth
Version: 0.0
Summary: jwt authentication
Author-email: nehayerpula@rangam.com
